sendemailpy3/__init__.py
sendemailpy3/sendemailpy3.py
SendEmailPy3-1.1.2.dist-info/LICENSE
SendEmailPy3-1.1.2.dist-info/METADATA
SendEmailPy3-1.1.2.dist-info/WHEEL
SendEmailPy3-1.1.2.dist-info/top_level.txt
SendEmailPy3-1.1.2.dist-info/RECORD
